spotipy_anon/__init__.py
spotipy_anon/oauth2.py
spotipy_anon-1.1.dist-info/LICENSE
spotipy_anon-1.1.dist-info/METADATA
spotipy_anon-1.1.dist-info/WHEEL
spotipy_anon-1.1.dist-info/top_level.txt
spotipy_anon-1.1.dist-info/RECORD
