Metadata-Version: 2.1
Name: spotipy-anon
Version: 1.1
Summary: An extension to Spotipy for anonymous access to the Spotify Web API
Home-page: https://github.com/dieser-niko/spotipy-anon
Author: @dieserniko
Author-email: dieserniko@gmx.de
License: MIT
Project-URL: Source, https://github.com/dieserniko/spotipy-anon
Platform: UNKNOWN
Requires-Dist: spotipy (>=2.23.0)
